shellodoro/__init__.py
shellodoro/config.py
shellodoro/formatting.py
shellodoro/prestart.py
shellodoro/shellodoro.py
shellodoro/tools.py
shellodoro/models/__init__.py
shellodoro/models/mode.py
shellodoro-1.1.2.dist-info/LICENSE
shellodoro-1.1.2.dist-info/METADATA
shellodoro-1.1.2.dist-info/WHEEL
shellodoro-1.1.2.dist-info/entry_points.txt
shellodoro-1.1.2.dist-info/top_level.txt
shellodoro-1.1.2.dist-info/RECORD
