Metadata-Version: 2.1
Name: shellodoro
Version: 1.1.2
Summary: Pomodoro timer right in your favorite terminal!
Home-page: https://github.com/stepan-zubkov/shellodoro
Author: StepanZubkov
Author-email: zubkovbackend@gmail.com
Keywords: pomodoro,timer,tool,cli
Classifier: Intended Audience :: End Users/Desktop
Classifier: License :: OSI Approved :: The Unlicense (Unlicense)
Classifier: Operating System :: POSIX :: Linux
Classifier: Programming Language :: Python :: 3
Requires-Python: >=3.6
License-File: LICENSE
Requires-Dist: click
Requires-Dist: plyer
